README.rst
obmenka.py
setup.py
obmenka.egg-info/PKG-INFO
obmenka.egg-info/SOURCES.txt
obmenka.egg-info/dependency_links.txt
obmenka.egg-info/entry_points.txt
obmenka.egg-info/not-zip-safe
obmenka.egg-info/requires.txt
obmenka.egg-info/top_level.txt