Metadata-Version: 1.1
Name: obmenka
Version: 0.1
Summary: Mac OS X UAH currency tracker
Home-page: https://github.com/hellysmile/obmenka
Author: hellysmile
Author-email: hellysmile@gmail.com
License: http://www.apache.org/licenses/LICENSE-2.0
Keywords: obmenka
Platform: UNKNOWN
Classifier: Programming Language :: Python :: 2
Classifier: Operating System :: MacOS :: MacOS X
